main.py
kopiluwak-0.2.dist-info/METADATA
kopiluwak-0.2.dist-info/WHEEL
kopiluwak-0.2.dist-info/top_level.txt
kopiluwak-0.2.dist-info/RECORD
