Metadata-Version: 2.1
Name: kopiluwak
Version: 0.2
Summary: kopiluwak bikin mencret
Author-email: amapa <amapa619@gmail.com>
Project-URL: Homepage, https://github.com/amapas/kopiluwak
Project-URL: repository, https://github.com/amapas/kopiluwak
Classifier: Programming Language :: Python :: 3
Classifier: License :: OSI Approved :: MIT License
Classifier: Operating System :: OS Independent
Requires-Python: >=3.8
Requires-Dist: kedongdong ==0.3
